gdstarter/__init__.py
gdstarter/main.py
gdstarter-0.0.1.dist-info/LICENSE
gdstarter-0.0.1.dist-info/METADATA
gdstarter-0.0.1.dist-info/WHEEL
gdstarter-0.0.1.dist-info/entry_points.txt
gdstarter-0.0.1.dist-info/top_level.txt
gdstarter-0.0.1.dist-info/RECORD
