Metadata-Version: 2.1
Name: gdstarter
Version: 0.0.1
Summary: A simple CLI tool for creating Godot projects.
License-File: LICENSE
Requires-Dist: inquirer
Requires-Dist: requests
Provides-Extra: dev
Requires-Dist: twine ; extra == 'dev'
